[
    {
        "type": "Entradas",
        "description": "Rabas",
        "price": 1590,
        "available": true,
        "source": "images/rabas-caseras.webp"
    },
    {
        "type": "Entradas",
        "description": "Pão",
        "price": 1600,
        "available": true,
        "source": "images/couvert-1.png"
    },
    {
        "type": "Entradas",
        "description": "Provoleta",
        "price": 990,
        "available": true,
        "source": "images/provoleta.png"
    },
    {
        "type": "Entradas",
        "description": "Bruschetta",
        "price": 1200,
        "available": true,
        "source": "images/bruschetta.jpg"
    },
    {
        "type": "Entradas",
        "description": "Picada ",
        "price": 1650,
        "available": true,
        "source": "images/EtuUs5Uwx_1200x0__1.jpg"
    },
    {
        "type": "Principales",
        "description": "Ojo de bife con papas asadas",
        "price": 1750,
        "available": true,
        "source": "images/ojo_de_bife.jpg"
    },
    {
        "type": "Principales",
        "description": "Pizza Caprese + Rucula ",
        "price": 1350,
        "available": true,
        "source": "images/pizzatomate1b.webp"
    },
    {
        "type": "Principales",
        "description": "Empanadas Variedades -",
        "price": 1650,
        "available": false,
        "source": "images/empanadas.webp"
    },
    {
        "type": "Principales",
        "description": "Entraña con puré rústico",
        "price": 1400,
        "available": true,
        "source": "images/entranas-trenzadas_1920x1080-thumbnail.jpg"
    },
    {
        "type": "Principales",
        "description": "Hamburguesa Cheddar + medallones extra",
        "price": 1650,
        "available": true,
        "source": "images/hamburguesa.webp"
    },
    {
        "type": "Principales",
        "description": "Napolitana + Guarnicion a eleccion",
        "price": 700,
        "available": true,
        "source": "images/milanesa-a-la-napolitana-con-guarnicion-de-papas-VLWFAANIWBGPFO4CSUHS7RYVVQ.jpg"
    },
    {
        "type": "Principales",
        "description": "Tenedor libre mixto",
        "price": 1650,
        "available": true,
        "source": "images/carnes-para-asado-argentino-paulina-cocina-recetas-1200x675.jpg"
    },
    {
        "type": "Postres",
        "description": "Volcán de chocolate",
        "price": 790,
        "available": true,
        "source": "images/volcan.jpg"
    },
    {
        "type": "Postres",
        "description": "Copa de frutas",
        "price": 200,
        "available": true,
        "source": "images/postres-veraniegos.jpg.webp"
    },
    {
        "type": "Postres",
        "description": "Mousse de chocolate",
        "price": 320,
        "available": true,
        "source": "images/Postres-para-restaurantes-faciles-de-preparar.jpg"
    },
    {
        "type": "Postres",
        "description": "Plátano flambeado con helado",
        "price": 590,
        "available": true,
        "source": "images/5-ideas-de-postres-para-restaurantes.jpg"
    },
    {
        "type": "Postres",
        "description": "Torta helada Frutilla",
        "price": 560,
        "available": true,
        "source": "images/7090fee9f7d606c31889aa40d310b8fa_torta_helada_de_merengue_sin_azúcar.jpg"
    },
    {
        "type": "Bebidas",
        "description": "Latas Variedad",
        "price": 210,
        "available": true,
        "source": "images/latagaseosas2.jpg"
    },
    {
        "type": "Bebidas",
        "description": "Jugo exprimido de naranja",
        "price": 400,
        "available": true,
        "source": "images/exprimido.jpg"
    },
    {
        "type": "Bebidas",
        "description": "Daikiri dulce + vodka limon",
        "price": 560,
        "available": false,
        "source": "images/limon.webp"
    },
    {
        "type": "Bebidas",
        "description": "Vino Tinto Amalaya Corte Único",
        "price": 1100,
        "available": true,
        "source": "images/vino_tinto.jpg"
    } 
    
]